{
  "original_image_path": "data\\original_images\\Photo 2024-01-27, 10 36 41.jpg",
  "image_path": "data\\images\\Photo-2024-01-27-10-36-41.jpg",
  "ut": 1706332001,
  "latlng": [
    6.968239,
    80.765358
  ],
  "alt": 1887.6559226430297,
  "direction": 283.884765625,
  "plantnet_results": [
    {
      "score": 0.69002,
      "species": {
        "scientificNameWithoutAuthor": "Impatiens hawkeri",
        "scientificNameAuthorship": "W.Bull",
        "genus": {
          "scientificNameWithoutAuthor": "Impatiens",
          "scientificNameAuthorship": "",
          "scientificName": "Impatiens"
        },
        "family": {
          "scientificNameWithoutAuthor": "Balsaminaceae",
          "scientificNameAuthorship": "",
          "scientificName": "Balsaminaceae"
        },
        "commonNames": [
          "New Guinea Impatiens",
          "Impatiens",
          "\u06af\u0644 \u062d\u0646\u0627"
        ],
        "scientificName": "Impatiens hawkeri W.Bull"
      },
      "gbif": {
        "id": "4193702"
      },
      "powo": {
        "id": "374127-1"
      }
    },
    {
      "score": 0.12787,
      "species": {
        "scientificNameWithoutAuthor": "Impatiens walleriana",
        "scientificNameAuthorship": "Hook.f.",
        "genus": {
          "scientificNameWithoutAuthor": "Impatiens",
          "scientificNameAuthorship": "",
          "scientificName": "Impatiens"
        },
        "family": {
          "scientificNameWithoutAuthor": "Balsaminaceae",
          "scientificNameAuthorship": "",
          "scientificName": "Balsaminaceae"
        },
        "commonNames": [
          "Busy lizzy",
          "\u06af\u0644 \u062d\u0646\u0627",
          "Buzzy lizzy"
        ],
        "scientificName": "Impatiens walleriana Hook.f."
      },
      "gbif": {
        "id": "2891772"
      },
      "powo": {
        "id": "374419-1"
      }
    },
    {
      "score": 0.02034,
      "species": {
        "scientificNameWithoutAuthor": "Impatiens balsamina",
        "scientificNameAuthorship": "L.",
        "genus": {
          "scientificNameWithoutAuthor": "Impatiens",
          "scientificNameAuthorship": "",
          "scientificName": "Impatiens"
        },
        "family": {
          "scientificNameWithoutAuthor": "Balsaminaceae",
          "scientificNameAuthorship": "",
          "scientificName": "Balsaminaceae"
        },
        "commonNames": [
          "Balsam",
          "Garden balsam",
          "Touch-me-not"
        ],
        "scientificName": "Impatiens balsamina L."
      },
      "gbif": {
        "id": "2891773"
      },
      "powo": {
        "id": "373978-1"
      }
    },
    {
      "score": 0.00655,
      "species": {
        "scientificNameWithoutAuthor": "Impatiens flaccida",
        "scientificNameAuthorship": "Arn.",
        "genus": {
          "scientificNameWithoutAuthor": "Impatiens",
          "scientificNameAuthorship": "",
          "scientificName": "Impatiens"
        },
        "family": {
          "scientificNameWithoutAuthor": "Balsaminaceae",
          "scientificNameAuthorship": "",
          "scientificName": "Balsaminaceae"
        },
        "commonNames": [
          "\u0c30\u0c3f\u0c15\u0c4d\u0c15 \u0c17\u0c4b\u0c30\u0c3f\u0c02\u0c1f",
          "Busy lizzy"
        ],
        "scientificName": "Impatiens flaccida Arn."
      },
      "gbif": {
        "id": "4193555"
      },
      "powo": {
        "id": "374090-1"
      }
    },
    {
      "score": 0.00303,
      "species": {
        "scientificNameWithoutAuthor": "Lobelia cardinalis",
        "scientificNameAuthorship": "L.",
        "genus": {
          "scientificNameWithoutAuthor": "Lobelia",
          "scientificNameAuthorship": "",
          "scientificName": "Lobelia"
        },
        "family": {
          "scientificNameWithoutAuthor": "Campanulaceae",
          "scientificNameAuthorship": "",
          "scientificName": "Campanulaceae"
        },
        "commonNames": [
          "Cardinal Flower",
          "Scarlet lobelia",
          "Red Cardinal Flower"
        ],
        "scientificName": "Lobelia cardinalis L."
      },
      "gbif": {
        "id": "5408269"
      },
      "powo": {
        "id": "142115-2"
      },
      "iucn": {
        "id": "64317175",
        "category": "LC"
      }
    }
  ]
}