{
  "ut_api_call": 1712289577.4359574,
  "plant_photo_id": "Photo-2024-04-05-07-45-54",
  "species_name_to_score": {
    "Fraxinus americana": 0.06592,
    "Fraxinus ornus": 0.06298,
    "Fraxinus chinensis": 0.04287,
    "Handroanthus ochraceus": 0.03685,
    "Steganotaenia araliacea": 0.03106,
    "Fraxinus profunda": 0.02937,
    "Fraxinus pennsylvanica": 0.02906,
    "Broussonetia papyrifera": 0.01796,
    "Bischofia javanica": 0.01534,
    "Koompassia malaccensis": 0.01352,
    "Quercus faginea": 0.01166,
    "Diospyros virginiana": 0.01097,
    "Pleiogynium timoriense": 0.01079,
    "Populus tomentosa": 0.00927,
    "Ptelea trifoliata": 0.00797,
    "Sassafras albidum": 0.00765,
    "Hovenia dulcis": 0.00743,
    "Fraxinus bungeana": 0.00723,
    "Fraxinus caroliniana": 0.00708,
    "Fraxinus excelsior": 0.00681,
    "Morus rubra": 0.00612,
    "Schismus barbatus": 0.00594,
    "Lindera communis": 0.0059,
    "Aralia warmingiana": 0.00499,
    "Cassia fistula": 0.00473,
    "Pterocarpus indicus": 0.00433,
    "Platymiscium parviflorum": 0.0042,
    "Citronella mucronata": 0.00399,
    "Celtis occidentalis": 0.00382,
    "Acer negundo": 0.00367,
    "Handroanthus heptaphyllus": 0.00359,
    "Homalium racemosum": 0.00354,
    "Pterocarpus erinaceus": 0.00348,
    "Juglans regia": 0.00339,
    "Millingtonia hortensis": 0.00313,
    "Quercus segoviensis": 0.00312,
    "Phellodendron amurense": 0.003,
    "Toona ciliata": 0.00292,
    "Schrebera alata": 0.00291,
    "Liriodendron tulipifera": 0.00291,
    "Bridelia micrantha": 0.00275,
    "Ulmus americana": 0.00268,
    "Aegle marmelos": 0.00262,
    "Handroanthus serratifolius": 0.00259,
    "Combretum apiculatum": 0.00258,
    "Rhamnus alpina": 0.0025,
    "Fraxinus velutina": 0.00239,
    "Handroanthus albus": 0.00232,
    "Tabebuia roseoalba": 0.00232,
    "Spathodea campanulata": 0.00229,
    "Juglans nigra": 0.00225,
    "Erythrina corallodendron": 0.00222,
    "Pterocarpus santalinus": 0.00217,
    "Acer monspessulanum": 0.00216,
    "Alnus cordata": 0.00213,
    "Maackia amurensis": 0.00209,
    "Timonius balansanus": 0.00205,
    "Polyscias repanda": 0.00201,
    "Erythrophleum suaveolens": 0.00196,
    "Handroanthus impetiginosus": 0.00195,
    "Dombeya kefaensis": 0.00193,
    "Herniaria latifolia": 0.00188,
    "Cladrastis kentukea": 0.00184,
    "Torminalis glaberrima": 0.00181,
    "Radermachera sinica": 0.0018,
    "Populus heterophylla": 0.00177,
    "Fraxinus uhdei": 0.00173,
    "Populus balsamifera": 0.00172,
    "Ligustrum lucidum": 0.0017,
    "Liriodendron chinense": 0.00164,
    "Koelreuteria paniculata": 0.00163,
    "Cinnamomum camphora": 0.00163,
    "Copaifera langsdorffii": 0.00162,
    "Erythrina brucei": 0.00162,
    "Toxicodendron radicans": 0.00161,
    "Erythrina falcata": 0.0016,
    "Morus nigra": 0.0016,
    "Lannea discolor": 0.00159,
    "Fraxinus floribunda": 0.00155,
    "Quercus pubescens": 0.00154,
    "Poecilanthe parviflora": 0.00154,
    "Magnolia loebneri": 0.00152,
    "Quercus pyrenaica": 0.00149,
    "Sclerocarya birrea": 0.00149,
    "Schotia brachypetala": 0.00146,
    "Acer truncatum": 0.00144,
    "Carya tomentosa": 0.00132,
    "Croton megalocarpus": 0.0013,
    "Choerospondias axillaris": 0.00125,
    "Ulmus glabra": 0.00124,
    "Corylus ferox": 0.00122,
    "Cornus florida": 0.00116,
    "Acer opalus": 0.00115,
    "Hura crepitans": 0.00113,
    "Platanus occidentalis": 0.00109,
    "Syzygium cumini": 0.00108,
    "Erythrina caffra": 0.00104,
    "Chukrasia tabularis": 0.00104,
    "Xanthophyllum eurhynchum": 0.00104,
    "Hennecartia omphalandra": 0.00102,
    "Myroxylon balsamum": 0.00102,
    "Pterocarpus rohrii": 0.00101
  }
}