{
  "ut_api_call": 0,
  "plant_photo_id": "Photo-2024-03-11-06-40-37",
  "species_name_to_score": {
    "Tecoma stans": 0.62464,
    "Handroanthus chrysanthus": 0.01227,
    "Handroanthus heptaphyllus": 0.01224,
    "Handroanthus chrysotrichus": 0.00608,
    "Dolichandra unguis-cati": 0.00576,
    "Roseodendron chryseum": 0.00563,
    "Tabernaemontana grandiflora": 0.00509,
    "Ctenodon compactus": 0.00503,
    "Allamanda cathartica": 0.005,
    "Impatiens noli-tangere": 0.00466,
    "Crotalaria laburnifolia": 0.00453,
    "Carpinus japonica": 0.0045,
    "Markhamia lutea": 0.00267,
    "Handroanthus albus": 0.00237,
    "Kerria japonica": 0.00207,
    "Allamanda schottii": 0.00193,
    "Senna surattensis": 0.00177,
    "Quiina guianensis": 0.00171,
    "Handroanthus serratifolius": 0.00171,
    "Tabernaemontana donnell-smithii": 0.00168,
    "Acrisione denticulata": 0.00149,
    "Theobroma cacao": 0.00143,
    "Arquita mimosifolia": 0.00141,
    "Cochlospermum vitifolium": 0.00132,
    "Senna multijuga": 0.0013,
    "Croton cortesianus": 0.00122,
    "Tipuana tipu": 0.00116,
    "Castanea dentata": 0.00113,
    "Tabebuia rosea": 0.00101
  }
}