{
  "ut_api_call": 1712115859.2919598,
  "plant_photo_id": "Photo-2024-04-03-07-37-17",
  "species_name_to_score": {
    "Terminalia arjuna": 0.22598,
    "Lagerstroemia speciosa": 0.0332,
    "Quercus laurifolia": 0.02674,
    "Quercus virginiana": 0.02662,
    "Lafoensia glyptocarpa": 0.02613,
    "Quercus phellos": 0.02483,
    "Quercus imbricaria": 0.0239,
    "Myrrhinium atropurpureum": 0.01112,
    "Schinus polygama": 0.01055,
    "Diospyros inconstans": 0.01052,
    "Quercus oglethorpensis": 0.01017,
    "Searsia natalensis": 0.0068,
    "Tabernaemontana laeta": 0.00572,
    "Ochna integerrima": 0.0047,
    "Asclepias curassavica": 0.0045,
    "Excoecaria cochinchinensis": 0.00415,
    "Scutia buxifolia": 0.00413,
    "Diospyros mespiliformis": 0.00413,
    "Periploca graeca": 0.00379,
    "Hymenopus macrophyllus": 0.00371,
    "Schinus longifolia": 0.00353,
    "Quercus engelmannii": 0.00338,
    "Ludwigia octovalvis": 0.00334,
    "Salix integra": 0.00325,
    "Cotoneaster frigidus": 0.00322,
    "Syzygium jambos": 0.00321,
    "Quercus fusiformis": 0.00278,
    "Woodfordia fruticosa": 0.00272,
    "Eugenia dysenterica": 0.00251,
    "Sapium glandulosum": 0.00248,
    "Glochidion billardierei": 0.00247,
    "Ludwigia erecta": 0.00247,
    "Inga densiflora": 0.00235,
    "Pterocarya stenoptera": 0.0023,
    "Elaeocarpus reticulatus": 0.00225,
    "Forsteronia spicata": 0.0022,
    "Dodonaea viscosa": 0.00215,
    "Passiflora laurifolia": 0.00198,
    "Madhuca longifolia": 0.00196,
    "Terminalia bentzoe": 0.00178,
    "Quercus humboldtii": 0.00176,
    "Crescentia cujete": 0.00173,
    "Couroupita guianensis": 0.00172,
    "Lithraea brasiliensis": 0.00165,
    "Pyracantha koidzumii": 0.00154,
    "Cichorium endivia": 0.00154,
    "Triplaris americana": 0.00152,
    "Lafoensia pacari": 0.0015,
    "Flueggea virosa": 0.00149,
    "Quercus nigra": 0.00148,
    "Eugenia pyriformis": 0.00147,
    "Salix eriocephala": 0.00147,
    "Salix triandra": 0.00141,
    "Salix pentandra": 0.00132,
    "Eugenia uniflora": 0.0013,
    "Psidium guajava": 0.0013,
    "Rauvolfia viridis": 0.00129,
    "Cratoxylum formosum": 0.00124,
    "Pseudobombax grandiflorum": 0.00123,
    "Salix daphnoides": 0.00117,
    "Terminalia sericea": 0.00117,
    "Chaenomeles speciosa": 0.00114,
    "Lecythis pisonis": 0.00112,
    "Ficus kerkhovenii": 0.00112,
    "Zygia longifolia": 0.00112,
    "Combretum kraussii": 0.00109,
    "Phyllanthus emblica": 0.00108,
    "Inga edulis": 0.00106,
    "Ludwigia alternifolia": 0.00106
  }
}