{
  "ut_api_call": 0,
  "plant_photo_id": "Photo-2024-03-11-06-43-58",
  "species_name_to_score": {
    "Khaya senegalensis": 0.13404,
    "Toona ciliata": 0.12081,
    "Terminalia arjuna": 0.10868,
    "Khaya anthotheca": 0.07234,
    "Hymenaea courbaril": 0.02615,
    "Bursera simaruba": 0.02223,
    "Syzygium borbonicum": 0.02061,
    "Ficus racemosa": 0.01771,
    "Beilschmiedia pendula": 0.00989,
    "Beilschmiedia roxburghiana": 0.00982,
    "Lophostemon confertus": 0.00785,
    "Aganope stuhlmannii": 0.00766,
    "Balfourodendron riedelianum": 0.00734,
    "Microcos paniculata": 0.0073,
    "Sideroxylon capiri": 0.00709,
    "Aucoumea klaineana": 0.00693,
    "Brosimum alicastrum": 0.00553,
    "Sideroxylon foetidissimum": 0.00507,
    "Plinia cauliflora": 0.00482,
    "Zanthoxylum rhoifolium": 0.00481,
    "Gironniera subaequalis": 0.0048,
    "Sapium glandulosum": 0.00464,
    "Astronium graveolens": 0.00458,
    "Combretum erythrophyllum": 0.0043,
    "Simarouba amara": 0.00421,
    "Copaifera langsdorffii": 0.00418,
    "Ocotea whitei": 0.00407,
    "Carapa guianensis": 0.00406,
    "Harpullia cupanioides": 0.00394,
    "Ficus variegata": 0.00393,
    "Parkia speciosa": 0.0038,
    "Cratoxylum cochinchinense": 0.00369,
    "Lophira alata": 0.0035,
    "Ceiba pentandra": 0.00339,
    "Stereospermum kunthianum": 0.00306,
    "Paronychia fastigiata": 0.00285,
    "Dimocarpus longan": 0.00266,
    "Machilus thunbergii": 0.00265,
    "Swietenia mahagoni": 0.00244,
    "Hevea brasiliensis": 0.00241,
    "Fraxinus griffithii": 0.00237,
    "Warburgia ugandensis": 0.00228,
    "Afzelia quanzensis": 0.00226,
    "Swietenia macrophylla": 0.00222,
    "Alphitonia excelsa": 0.00213,
    "Trichilia emetica": 0.00209,
    "Pterocarpus rohrii": 0.00207,
    "Pittosporum ferrugineum": 0.00206,
    "Inga edulis": 0.00203,
    "Flacourtia rukam": 0.00203,
    "Agathis lanceolata": 0.00202,
    "Cupania glabra": 0.002,
    "Vochysia ferruginea": 0.00194,
    "Cassia grandis": 0.0019,
    "Handroanthus serratifolius": 0.00184,
    "Apuleia leiocarpa": 0.00176,
    "Cossinia pinnata": 0.00174,
    "Beilschmiedia erythrophloia": 0.00169,
    "Diospyros fasciculosa": 0.00164,
    "Genipa americana": 0.0016,
    "Pometia pinnata": 0.00159,
    "Syzygium cumini": 0.00154,
    "Ficus sycomorus": 0.00151,
    "Cunonia capensis": 0.00146,
    "Ocotea acutifolia": 0.00145,
    "Ficus salicifolia": 0.00143,
    "Nectandra angustifolia": 0.00141,
    "Persea indica": 0.0014,
    "Senna siamea": 0.00138,
    "Gardenia urvillei": 0.00136,
    "Anadenanthera colubrina": 0.00135,
    "Casimiroa edulis": 0.00134,
    "Maclura tinctoria": 0.00133,
    "Aglaia elaeagnoidea": 0.00125,
    "Canarium album": 0.00124,
    "Simarouba glauca": 0.0012,
    "Litchi chinensis": 0.00117,
    "Ulmus parvifolia": 0.00114,
    "Daniellia oliveri": 0.00112,
    "Calycophyllum spruceanum": 0.00112,
    "Lithraea molleoides": 0.00109,
    "Cupania americana": 0.00108,
    "Cassia fistula": 0.00104,
    "Dalbergia tonkinensis": 0.00103,
    "Castanea seguinii": 0.00102
  }
}