{
  "ut_api_call": 1711522691.3234189,
  "plant_photo_id": "Photo-2024-03-08-06-58-01",
  "species_name_to_score": {
    "Lagerstroemia speciosa": 0.09807,
    "Tectona grandis": 0.07413,
    "Magnolia kobus": 0.0459,
    "Holarrhena pubescens": 0.04488,
    "Syzygium samarangense": 0.0341,
    "Magnolia acuminata": 0.03163,
    "Triplaris americana": 0.02658,
    "Nephelium lappaceum": 0.02374,
    "Psidium guajava": 0.02279,
    "Annona purpurea": 0.01971,
    "Terminalia catappa": 0.01966,
    "Magnolia macrophylla": 0.01725,
    "Brugmansia versicolor": 0.01169,
    "Magnolia tripetala": 0.01069,
    "Syzygium aqueum": 0.00808,
    "Tabebuia rosea": 0.00803,
    "Bunchosia armeniaca": 0.00719,
    "Anacardium occidentale": 0.00693,
    "Asimina triloba": 0.00668,
    "Annona cherimola": 0.00651,
    "Theobroma cacao": 0.00591,
    "Juglans regia": 0.00566,
    "Magnolia obovata": 0.00553,
    "Bauhinia purpurea": 0.00532,
    "Syzygium malaccense": 0.00495,
    "Magnolia sieboldii": 0.00468,
    "Magnolia liliiflora": 0.00394,
    "Triplaris weigeltiana": 0.00368,
    "Ulmus uyematsui": 0.0035,
    "Handroanthus ochraceus": 0.00329,
    "Sterculia monosperma": 0.00311,
    "Quercus serrata": 0.00267,
    "Tabebuia roseoalba": 0.00257,
    "Castanea dentata": 0.00249,
    "Theobroma grandiflorum": 0.00247,
    "Neolamarckia macrophylla": 0.00243,
    "Aesculus pavia": 0.0024,
    "Megaskepasma erythrochlamys": 0.00233,
    "Lafoensia pacari": 0.00227,
    "Handroanthus impetiginosus": 0.00222,
    "Cordia superba": 0.00217,
    "Cordia dichotoma": 0.00214,
    "Ulmus glabra": 0.0021,
    "Quercus pontica": 0.00209,
    "Tabernaemontana pachysiphon": 0.00193,
    "Dillenia suffruticosa": 0.00186,
    "Pseudobombax ellipticum": 0.00172,
    "Inga spectabilis": 0.00171,
    "Tabernaemontana elegans": 0.00169,
    "Litsea monopetala": 0.00167,
    "Coccoloba acuminata": 0.00164,
    "Syzygium cumini": 0.0016,
    "Cordia sebestena": 0.00154,
    "Varronia curassavica": 0.00152,
    "Quercus rugosa": 0.0015,
    "Petrea volubilis": 0.0015,
    "Quercus polymorpha": 0.00148,
    "Barringtonia acutangula": 0.00147,
    "Bauhinia variegata": 0.00146,
    "Euphorbia pulcherrima": 0.00145,
    "Cassia fistula": 0.00145,
    "Dillenia reticulata": 0.00142,
    "Brugmansia suaveolens": 0.00142,
    "Bauhinia monandra": 0.00141,
    "Tabernaemontana grandiflora": 0.00138,
    "Magnolia soulangeana": 0.00135,
    "Vangueria infausta": 0.00135,
    "Caryocar brasiliense": 0.00133,
    "Plumeria rubra": 0.00129,
    "Warszewiczia coccinea": 0.00127,
    "Quercus aliena": 0.00126,
    "Spathodea campanulata": 0.00124,
    "Quercus michauxii": 0.00119,
    "Gomphrena pulchella": 0.00115,
    "Monodora tenuifolia": 0.00115,
    "Acer maximowiczianum": 0.00111,
    "Neocarya macrophylla": 0.0011,
    "Alnus acuminata": 0.0011,
    "Chonemorpha fragrans": 0.00108,
    "Iochroma arborescens": 0.00107,
    "Thalia multiflora": 0.00107,
    "Sabatia gentianoides": 0.00103,
    "Bauhinia blakeana": 0.00102,
    "Delostoma integrifolium": 0.00101
  }
}